MANIFEST.in
README.md
setup.py
ooktools/__init__.py
ooktools/console.py
ooktools/utilities.py
ooktools/validators.py
ooktools.egg-info/PKG-INFO
ooktools.egg-info/SOURCES.txt
ooktools.egg-info/dependency_links.txt
ooktools.egg-info/entry_points.txt
ooktools.egg-info/requires.txt
ooktools.egg-info/top_level.txt
ooktools/commands/__init__.py
ooktools/commands/converstions.py
ooktools/commands/graphing.py
ooktools/commands/grc.py
ooktools/commands/information.py
ooktools/commands/signalling.py
ooktools/share/template.grc