Metadata-Version: 1.1
Name: ooktools
Version: 1.4
Summary: On-off keying tools for your SDR
Home-page: https://github.com/leonjza/ooktools
Author: Leon Jacobs
Author-email: leonja511@gmail.com
License: UNKNOWN
Download-URL: https://github.com/leonjza/ooktools/tarball/1.4
Keywords: sdr,on-off,keying,rfcat,radio
Platform: UNKNOWN
